MANIFEST.in
README.rst
README.txt
distribute_setup.py
fabfile.py
setup.cfg
setup.py
plug/__init__.py
plug/cmd.py
plug.egg-info/PKG-INFO
plug.egg-info/SOURCES.txt
plug.egg-info/dependency_links.txt
plug.egg-info/entry_points.txt
plug.egg-info/requires.txt
plug.egg-info/top_level.txt
plug.egg-info/zip-safe