Metadata-Version: 1.0
Name: plug
Version: 0.1.0
Summary: A tool for creating pluggable web-processes for deployment 
Home-page: https://github.com/philipcristiano/plug
Author: Philip Cristiano
Author-email: plug@philipcristiano.com
License: BSD
Keywords: deployment packaging
Platform: UNKNOWN
Classifier: Development Status :: 2 - Pre-Alpha
Classifier: Intended Audience :: Developers
Classifier: License :: OSI Approved :: BSD License
Classifier: Operating System :: MacOS :: MacOS X
Classifier: Operating System :: POSIX
Classifier: Programming Language :: Python
